GuanyuLiulanqiHeWangluoDe20XiangXuzhi/README.md
GuanyuLiulanqiHeWangluoDe20XiangXuzhi/__init__.py
GuanyuLiulanqiHeWangluoDe20XiangXuzhi/__main__.py
GuanyuLiulanqiHeWangluoDe20XiangXuzhi/file.epub
GuanyuLiulanqiHeWangluoDe20XiangXuzhi/index.html
GuanyuLiulanqiHeWangluoDe20XiangXuzhi/css/__init__.py
GuanyuLiulanqiHeWangluoDe20XiangXuzhi/css/annotations.css
GuanyuLiulanqiHeWangluoDe20XiangXuzhi/css/main.css
GuanyuLiulanqiHeWangluoDe20XiangXuzhi/css/normalize.css
GuanyuLiulanqiHeWangluoDe20XiangXuzhi/css/popup.css
GuanyuLiulanqiHeWangluoDe20XiangXuzhi/font/__init__.py
GuanyuLiulanqiHeWangluoDe20XiangXuzhi/font/fontello.eot
GuanyuLiulanqiHeWangluoDe20XiangXuzhi/font/fontello.svg
GuanyuLiulanqiHeWangluoDe20XiangXuzhi/font/fontello.ttf
GuanyuLiulanqiHeWangluoDe20XiangXuzhi/font/fontello.woff
GuanyuLiulanqiHeWangluoDe20XiangXuzhi/img/__init__.py
GuanyuLiulanqiHeWangluoDe20XiangXuzhi/img/annotator-glyph-sprite.png
GuanyuLiulanqiHeWangluoDe20XiangXuzhi/img/annotator-icon-sprite.png
GuanyuLiulanqiHeWangluoDe20XiangXuzhi/img/apple-touch-icon.png
GuanyuLiulanqiHeWangluoDe20XiangXuzhi/img/cancelfullscreen.png
GuanyuLiulanqiHeWangluoDe20XiangXuzhi/img/close.png
GuanyuLiulanqiHeWangluoDe20XiangXuzhi/img/fullscreen.png
GuanyuLiulanqiHeWangluoDe20XiangXuzhi/img/loader.gif
GuanyuLiulanqiHeWangluoDe20XiangXuzhi/img/menu-icon.png
GuanyuLiulanqiHeWangluoDe20XiangXuzhi/img/save.png
GuanyuLiulanqiHeWangluoDe20XiangXuzhi/img/saved.png
GuanyuLiulanqiHeWangluoDe20XiangXuzhi/img/settings-s.png
GuanyuLiulanqiHeWangluoDe20XiangXuzhi/img/settings.png
GuanyuLiulanqiHeWangluoDe20XiangXuzhi/img/star.png
GuanyuLiulanqiHeWangluoDe20XiangXuzhi/js/__init__.py
GuanyuLiulanqiHeWangluoDe20XiangXuzhi/js/epub.js
GuanyuLiulanqiHeWangluoDe20XiangXuzhi/js/epub.min.js
GuanyuLiulanqiHeWangluoDe20XiangXuzhi/js/epub.min.map
GuanyuLiulanqiHeWangluoDe20XiangXuzhi/js/hooks.min.js
GuanyuLiulanqiHeWangluoDe20XiangXuzhi/js/hooks.min.map
GuanyuLiulanqiHeWangluoDe20XiangXuzhi/js/reader.js
guanyu_liulanqi_he_wangluo_de_20_xiang_xuzhi-2024.3.1.0.dist-info/METADATA
guanyu_liulanqi_he_wangluo_de_20_xiang_xuzhi-2024.3.1.0.dist-info/WHEEL
guanyu_liulanqi_he_wangluo_de_20_xiang_xuzhi-2024.3.1.0.dist-info/entry_points.txt
guanyu_liulanqi_he_wangluo_de_20_xiang_xuzhi-2024.3.1.0.dist-info/top_level.txt
guanyu_liulanqi_he_wangluo_de_20_xiang_xuzhi-2024.3.1.0.dist-info/RECORD
